Metadata-Version: 2.4
Name: plot-misc
Version: 2.0.4
Summary: Various plotting templates built on top of matplotlib
Author-email: A Floriaan Schmidt <floriaanschmidt@gmail.com>
License-Expression: GPL-3.0-or-later
Project-URL: Homepage, https://gitlab.com/SchmidtAF/plot-misc
Project-URL: Documentation, https://schmidtaf.gitlab.io/plot-misc/
Classifier: Programming Language :: Python
Classifier: Programming Language :: Python :: 3
Classifier: Programming Language :: Python :: 3.10
Classifier: Programming Language :: Python :: 3.11
Classifier: Programming Language :: Python :: 3.12
Classifier: Programming Language :: Python :: Implementation :: PyPy
Requires-Python: <3.13,>=3.10
License-File: LICENSE
Requires-Dist: pandas>=1.3
Requires-Dist: numpy>=1.21
Requires-Dist: matplotlib>=3.5
Requires-Dist: seaborn>=0.11
Requires-Dist: scipy>=1.5
Requires-Dist: statsmodels>=0.1
Requires-Dist: scikit-learn>=1.4
Requires-Dist: adjustText>=1.3
Provides-Extra: dev
Requires-Dist: python-build; extra == "dev"
Requires-Dist: twine; extra == "dev"
Requires-Dist: setuptools; extra == "dev"
Requires-Dist: wheel; extra == "dev"
Requires-Dist: pytest>=6; extra == "dev"
Requires-Dist: pytest-mock>=3; extra == "dev"
Requires-Dist: pytest-dependency>=0.5; extra == "dev"
Requires-Dist: bump2version>=1; extra == "dev"
Requires-Dist: jupyter; extra == "dev"
Dynamic: license-file
